4x16 decoder/design.v
module dec_4x16(
    input           en,
    input   [3:0]   in,
    output  [15:0]  out
);

    assign out = en ? 1 << in : 0;
endmodule

4x16 decoder/tb.v
module tb();
    reg             en;
    reg     [3:0]   in;
    wire    [15:0]  out;
    integer         i;

    dec_4x16 dut(
        .en(en),
        .in(in),
        .out(out)
    );

    initial begin
        $dumpfile("design.vcd");
        $dumpvars(0, tb);

        en <= 0;
        in <= 0;

        $monitor("en=%0b in=%4b out=%16b", en, in, out);

        for (i = 0; i < 32; i = i + 1) begin
            {en, in} = i;
            #10;
        end
    end
endmodule

4x16 decoder/design.vcd
$date
	Thu Mar 20 01:40:54 2025
$end
$version
	Icarus Verilog
$end
$timescale
	1s
$end
$scope module tb $end
$var wire 16 ! out [15:0] $end
$var reg 1 " en $end
$var reg 4 # in [3:0] $end
$var integer 32 $ i [31:0] $end
$scope module dut $end
$var wire 1 " en $end
$var wire 4 % in [3:0] $end
$var wire 16 & out [15:0] $end
$upscope $end
$upscope $end
$enddefinitions $end
#0
$dumpvars
b0 &
b0 %
b0 $
b0 #
0"
b0 !
$end
#10
b1 #
b1 %
b1 $
#20
b10 #
b10 %
b10 $
#30
b11 #
b11 %
b11 $
#40
b100 #
b100 %
b100 $
#50
b101 #
b101 %
b101 $
#60
b110 #
b110 %
b110 $
#70
b111 #
b111 %
b111 $
#80
b1000 #
b1000 %
b1000 $
#90
b1001 #
b1001 %
b1001 $
#100
b1010 #
b1010 %
b1010 $
#110
b1011 #
b1011 %
b1011 $
#120
b1100 #
b1100 %
b1100 $
#130
b1101 #
b1101 %
b1101 $
#140
b1110 #
b1110 %
b1110 $
#150
b1111 #
b1111 %
b1111 $
#160
b1 !
b1 &
1"
b0 #
b0 %
b10000 $
#170
b10 !
b10 &
b1 #
b1 %
b10001 $
#180
b100 !
b100 &
b10 #
b10 %
b10010 $
#190
b1000 !
b1000 &
b11 #
b11 %
b10011 $
#200
b10000 !
b10000 &
b100 #
b100 %
b10100 $
#210
b100000 !
b100000 &
b101 #
b101 %
b10101 $
#220
b1000000 !
b1000000 &
b110 #
b110 %
b10110 $
#230
b10000000 !
b10000000 &
b111 #
b111 %
b10111 $
#240
b100000000 !
b100000000 &
b1000 #
b1000 %
b11000 $
#250
b1000000000 !
b1000000000 &
b1001 #
b1001 %
b11001 $
#260
b10000000000 !
b10000000000 &
b1010 #
b1010 %
b11010 $
#270
b100000000000 !
b100000000000 &
b1011 #
b1011 %
b11011 $
#280
b1000000000000 !
b1000000000000 &
b1100 #
b1100 %
b11100 $
#290
b10000000000000 !
b10000000000000 &
b1101 #
b1101 %
b11101 $
#300
b100000000000000 !
b100000000000000 &
b1110 #
b1110 %
b11110 $
#310
b1000000000000000 !
b1000000000000000 &
b1111 #
b1111 %
b11111 $
#320
b100000 $
