full adder/design.v
module fa(
    input a,
    input b,
    input cin,
    output sum,
    output cout
);

    assign sum = (a ^ b) ^ cin;
    assign cout = (a & b) | ((a ^ b) & cin);
endmodule

full adder/tb.v
module tb();
    reg a;
    reg b;
    reg cin;
    wire sum;
    wire cout;
    integer i;

    fa dut(
        .a(a),
        .b(b),
        .cin(cin),
        .sum(sum),
        .cout(cout)
    );

    initial begin
        $dumpfile("design.vcd");
        $dumpvars(0, tb);

        a <= 0;
        b <= 0;
        cin <= 0;

        $monitor("a=%0b b=%0b cin=%0b sum=%0b cout=%0b", a, b, cin, sum, cout);

        for (i = 0 ; i < 8; i = i + 1) begin
            {a, b, cin} = i;
            #10;
        end
    end
endmodule

full adder/design.vcd
$date
	Thu Mar 20 00:01:28 2025
$end
$version
	Icarus Verilog
$end
$timescale
	1s
$end
$scope module tb $end
$var wire 1 ! sum $end
$var wire 1 " cout $end
$var reg 1 # a $end
$var reg 1 $ b $end
$var reg 1 % cin $end
$var integer 32 & i [31:0] $end
$scope module dut $end
$var wire 1 # a $end
$var wire 1 $ b $end
$var wire 1 % cin $end
$var wire 1 " cout $end
$var wire 1 ! sum $end
$upscope $end
$upscope $end
$enddefinitions $end
#0
$dumpvars
b0 &
0%
0$
0#
0"
0!
$end
#10
1!
1%
b1 &
#20
1!
1$
0%
b10 &
#30
1"
0!
1%
b11 &
#40
0"
1!
1#
0$
0%
b100 &
#50
1"
0!
1%
b101 &
#60
0!
1$
0%
b110 &
#70
1!
1%
b111 &
#80
b1000 &
