modulo-10 counter/design.v
module mod10_counter(
    input clk,
    input rstn,
    output reg [3:0] out
);

    always @(posedge clk or negedge rstn) begin
        if(!rstn) begin
            out <= 0;
        end
        else begin
            if(out == 10)
                out <= 0;
            else
                out <= out + 1;
        end
    end
endmodule

modulo-10 counter/tb.v
module tb();
    reg clk;
    reg rstn;
    wire [3:0] out;

    mod10_counter dut(
        .clk(clk),
        .rstn(rstn),
        .out(out)
    );

    always #5 clk = ~clk;

    initial begin
        $dumpfile("design.vcd");
        $dumpvars(0, tb);

        {clk, rstn} <= 0;

        #10 rstn <= 1;
        #400 $finish;
    end
endmodule

modulo-10 counter/design.vcd
$date
	Thu Mar 20 16:29:50 2025
$end
$version
	Icarus Verilog
$end
$timescale
	1s
$end
$scope module tb $end
$var wire 4 ! out [3:0] $end
$var reg 1 " clk $end
$var reg 1 # rstn $end
$scope module dut $end
$var wire 1 " clk $end
$var wire 1 # rstn $end
$var reg 4 $ out [3:0] $end
$upscope $end
$upscope $end
$enddefinitions $end
#0
$dumpvars
b0 $
0#
0"
b0 !
$end
#5
1"
#10
1#
0"
#15
b1 !
b1 $
1"
#20
0"
#25
b10 !
b10 $
1"
#30
0"
#35
b11 !
b11 $
1"
#40
0"
#45
b100 !
b100 $
1"
#50
0"
#55
b101 !
b101 $
1"
#60
0"
#65
b110 !
b110 $
1"
#70
0"
#75
b111 !
b111 $
1"
#80
0"
#85
b1000 !
b1000 $
1"
#90
0"
#95
b1001 !
b1001 $
1"
#100
0"
#105
b1010 !
b1010 $
1"
#110
0"
#115
b0 !
b0 $
1"
#120
0"
#125
b1 !
b1 $
1"
#130
0"
#135
b10 !
b10 $
1"
#140
0"
#145
b11 !
b11 $
1"
#150
0"
#155
b100 !
b100 $
1"
#160
0"
#165
b101 !
b101 $
1"
#170
0"
#175
b110 !
b110 $
1"
#180
0"
#185
b111 !
b111 $
1"
#190
0"
#195
b1000 !
b1000 $
1"
#200
0"
#205
b1001 !
b1001 $
1"
#210
0"
#215
b1010 !
b1010 $
1"
#220
0"
#225
b0 !
b0 $
1"
#230
0"
#235
b1 !
b1 $
1"
#240
0"
#245
b10 !
b10 $
1"
#250
0"
#255
b11 !
b11 $
1"
#260
0"
#265
b100 !
b100 $
1"
#270
0"
#275
b101 !
b101 $
1"
#280
0"
#285
b110 !
b110 $
1"
#290
0"
#295
b111 !
b111 $
1"
#300
0"
#305
b1000 !
b1000 $
1"
#310
0"
#315
b1001 !
b1001 $
1"
#320
0"
#325
b1010 !
b1010 $
1"
#330
0"
#335
b0 !
b0 $
1"
#340
0"
#345
b1 !
b1 $
1"
#350
0"
#355
b10 !
b10 $
1"
#360
0"
#365
b11 !
b11 $
1"
#370
0"
#375
b100 !
b100 $
1"
#380
0"
#385
b101 !
b101 $
1"
#390
0"
#395
b110 !
b110 $
1"
#400
0"
#405
b111 !
b111 $
1"
